LICENSE
MANIFEST.in
README.md
setup.cfg
setup.py
x_msgpack.py
x_msgpack.egg-info/PKG-INFO
x_msgpack.egg-info/SOURCES.txt
x_msgpack.egg-info/dependency_links.txt
x_msgpack.egg-info/top_level.txt