Metadata-Version: 2.1
Name: x-msgpack
Version: 0.2.0
Summary: Simple MessagePack implementation with custom extensions.
Home-page: https://github.com/ShenTengTu/x_msgpack
Author: Shen-Teng Tu
Author-email: tusamten@gmail.com
License: MIT
Keywords: Python msgpack
Platform: UNKNOWN
Classifier: Development Status :: 5 - Production/Stable
Classifier: Intended Audience :: Developers
Classifier: License :: OSI Approved :: MIT License
Classifier: Programming Language :: Python :: 3
Classifier: Programming Language :: Python :: Implementation :: CPython
Classifier: Topic :: Software Development
